davi_bot_api_consumer/__init__.py
davi_bot_api_consumer/exceptions_davi.py
davi_bot_api_consumer-0.1.0.dist-info/METADATA
davi_bot_api_consumer-0.1.0.dist-info/WHEEL
davi_bot_api_consumer-0.1.0.dist-info/RECORD
