Metadata-Version: 2.1
Name: davi-bot-api-consumer
Version: 0.1.0
Summary: 
Author: Leonardo Vieira - Fontes
Author-email: leonardo.vieira@jeaholding.com.br
Requires-Python: >=3.8,<4.0
Classifier: Programming Language :: Python :: 3
Classifier: Programming Language :: Python :: 3.8
Classifier: Programming Language :: Python :: 3.9
Classifier: Programming Language :: Python :: 3.10
Classifier: Programming Language :: Python :: 3.11
Requires-Dist: requests (>=2.27.1,<3.0.0)
